cache_client/__init__.py
cache_client/backend/__init__.py
cache_client/backend/base.py
cache_client/backend/mysql.py
cache_client/cache/__init__.py
cache_client/cache/base.py
cache_client/cache/redis.py
cache_client/client/__init__.py
cache_client/client/base.py
cache_client/client/common.py
cache_client/dump_tool/__init__.py
cache_client/dump_tool/base.py
cache_client/dump_tool/yaml_tool.py
cache_client-1.0.0.dist-info/METADATA
cache_client-1.0.0.dist-info/WHEEL
cache_client-1.0.0.dist-info/top_level.txt
cache_client-1.0.0.dist-info/RECORD
