Metadata-Version: 2.1
Name: cache-client
Version: 1.0.0
Summary: README.md
Home-page: https://github.com/aohan237/cache_client
Author: aohan237
Author-email: aohan237@gmail.com
License: BSD
Keywords: asyncio cache client
Platform: any
Classifier: Development Status :: 5 - Production/Stable
Classifier: License :: OSI Approved :: BSD License
Classifier: Programming Language :: Python
Classifier: Programming Language :: Python :: 3
Classifier: Programming Language :: Python :: 3.5
Classifier: Programming Language :: Python :: 3.6
Classifier: Programming Language :: Python :: 3.7
Classifier: Programming Language :: Python :: Implementation :: CPython
Classifier: Programming Language :: Python :: Implementation :: PyPy
Classifier: Operating System :: OS Independent
Classifier: Topic :: Communications
Classifier: Topic :: System :: Distributed Computing
Classifier: Topic :: Software Development :: Libraries :: Python Modules
Requires-Dist: aiomysql (>=0.0.20)
Requires-Dist: aioredis (>=1.2.0)
Requires-Dist: pyyaml (>=5.1)
